LICENSE.txt
README.md
setup.py
subway_detector/__init__.py
subway_detector/main.py
subway_detector/subway_detector.py
subway_detector.egg-info/PKG-INFO
subway_detector.egg-info/SOURCES.txt
subway_detector.egg-info/dependency_links.txt
subway_detector.egg-info/entry_points.txt
subway_detector.egg-info/requires.txt
subway_detector.egg-info/top_level.txt
subway_detector/classifier/__init__.py
subway_detector/classifier/class_net_test.py
subway_detector/detector/__init__.py
subway_detector/detector/detect.py
subway_detector/detector/utils/__init__.py
subway_detector/detector/utils/nms_iou.py
subway_detector/model/__init__.py
subway_detector/model/net/__init__.py
subway_detector/model/net/resNet.py
subway_detector/utils/__init__.py
subway_detector/utils/transform.py
subway_detector/utils/visualization.py